csv_utilities/__init__.py
csv_utilities/csv.py
csv_utilities-0.3.0.dist-info/METADATA
csv_utilities-0.3.0.dist-info/WHEEL
csv_utilities-0.3.0.dist-info/top_level.txt
csv_utilities-0.3.0.dist-info/RECORD
