Metadata-Version: 2.1
Name: csv-utilities
Version: 0.3.0
Summary: A simple, no-dependency Python CSV library.
Home-page: https://github.com/cowalla/CSVUtilities
Author: Connor Wallace
Author-email: wallaconno@gmail.com
License: UNKNOWN
Platform: UNKNOWN
Classifier: License :: OSI Approved :: MIT License
